map_maker/__init__.py
map_maker/_version.py
map_maker/cli.py
map_maker/bokeh/__init__.py
map_maker/bokeh/map_maker.py
map_maker/folium/__init__.py
map_maker/folium/map_maker.py
map_maker/util/__init__.py
map_maker/util/util.py
map_maker-1.4.3.dist-info/LICENSE
map_maker-1.4.3.dist-info/METADATA
map_maker-1.4.3.dist-info/WHEEL
map_maker-1.4.3.dist-info/entry_points.txt
map_maker-1.4.3.dist-info/top_level.txt
map_maker-1.4.3.dist-info/RECORD
