Metadata-Version: 2.1
Name: map-maker
Version: 1.4.3
Summary: UNKNOWN
Home-page: https://github.com/ExpediaGroup/map-maker
Author: Tim Renner
License: Apache 2.0
Platform: UNKNOWN
Classifier: Development Status :: 4 - Beta
Classifier: License :: OSI Approved :: Apache Software License
Classifier: Programming Language :: Python :: 3.6
Classifier: Programming Language :: Python :: 3.7
Classifier: Programming Language :: Python :: 3.8
Requires-Dist: click (>=7.0)
Requires-Dist: toolz (>=0.9)
Requires-Dist: bokeh (>=1.1.0)
Requires-Dist: Shapely (>=1.6.4.post2)
Requires-Dist: pyproj (<2,>=1.9.5.1)
Requires-Dist: folium (<1,>=0.10.0)
